{
  "url":"https://api.github.com/repos/athensresearch/athens/pulls/comments/449238655",
  "pull_request_review_id":441983713,
  "id":449238655,
  "node_id":"MDI0OlB1bGxSZXF1ZXN0UmV2aWV3Q29tbWVudDQ0OTIzODY1NQ==",
  "diff_hunk":"@@ -263,12 +267,29 @@\n \n (defn results-el\n   []\n-  [:div (use-style results-heading-style)\n-   [:h5 \"Results\"]\n-   [:span (use-style hint-style)\n-    \"Press \"\n-    [:kbd \"shift + enter\"]\n-    \" to open in right sidebar.\"]])\n+  (let [show-recent? @(subscribe [:show-recent?])\n+        recent-item-length 40\n+        style-display {:style {:display (if show-recent? \"block\" \"none\")}}]\n+    [:<> [:div (use-style results-heading-style)\n+          [:h5 (if show-recent? \"Recent\" \"Results\")]\n+          [:span (use-style hint-style)\n+           \"Press \"\n+           [:kbd \"shift + enter\"]\n+           \" to open in right sidebar.\"]]\n+     [:div (merge (use-style results-list-style) style-display)",
  "path":"src/cljs/athens/devcards/athena.cljs",
  "position":null,
  "original_position":48,
  "commit_id":"93fdb08d2ea2eaf07a5004bbadcce682dcd15276",
  "original_commit_id":"8f3de4e561ca55104f3c5aee5f8f89cd36205aff",
  "user":{
    "login":"prabhath6",
    "id":10682370,
    "node_id":"MDQ6VXNlcjEwNjgyMzcw",
    "avatar_url":"https://avatars0.githubusercontent.com/u/10682370?v=4",
    "gravatar_id":"",
    "url":"https://api.github.com/users/prabhath6",
    "html_url":"https://github.com/prabhath6",
    "followers_url":"https://api.github.com/users/prabhath6/followers",
    "following_url":"https://api.github.com/users/prabhath6/following{/other_user}",
    "gists_url":"https://api.github.com/users/prabhath6/gists{/gist_id}",
    "starred_url":"https://api.github.com/users/prabhath6/starred{/owner}{/repo}",
    "subscriptions_url":"https://api.github.com/users/prabhath6/subscriptions",
    "organizations_url":"https://api.github.com/users/prabhath6/orgs",
    "repos_url":"https://api.github.com/users/prabhath6/repos",
    "events_url":"https://api.github.com/users/prabhath6/events{/privacy}",
    "received_events_url":"https://api.github.com/users/prabhath6/received_events",
    "type":"User",
    "site_admin":false
  },
  "body":"i took a look at code again and the query term is stored in an atom that can be passed to `results-el`.",
  "created_at":"2020-07-02 19:59:59 UTC",
  "updated_at":"2020-07-04 18:06:55 UTC",
  "html_url":"https://github.com/athensresearch/athens/pull/208#discussion_r449238655",
  "pull_request_url":"https://api.github.com/repos/athensresearch/athens/pulls/208",
  "author_association":"MEMBER",
  "_links":{
    "self":{
      "href":"https://api.github.com/repos/athensresearch/athens/pulls/comments/449238655"
    },
    "html":{
      "href":"https://github.com/athensresearch/athens/pull/208#discussion_r449238655"
    },
    "pull_request":{
      "href":"https://api.github.com/repos/athensresearch/athens/pulls/208"
    }
  },
  "start_line":null,
  "original_start_line":272,
  "start_side":"RIGHT",
  "line":null,
  "original_line":279,
  "side":"RIGHT",
  "in_reply_to_id":449174886
}