{
  "url":"https://api.github.com/repos/athensresearch/athens/issues/65",
  "repository_url":"https://api.github.com/repos/athensresearch/athens",
  "labels_url":"https://api.github.com/repos/athensresearch/athens/issues/65/labels{/name}",
  "comments_url":"https://api.github.com/repos/athensresearch/athens/issues/65/comments",
  "events_url":"https://api.github.com/repos/athensresearch/athens/issues/65/events",
  "html_url":"https://github.com/athensresearch/athens/issues/65",
  "id":619327243,
  "node_id":"MDU6SXNzdWU2MTkzMjcyNDM=",
  "number":65,
  "title":"Link Filters",
  "user":{
    "login":"tangjeff0",
    "id":8952138,
    "node_id":"MDQ6VXNlcjg5NTIxMzg=",
    "avatar_url":"https://avatars1.githubusercontent.com/u/8952138?v=4",
    "gravatar_id":"",
    "url":"https://api.github.com/users/tangjeff0",
    "html_url":"https://github.com/tangjeff0",
    "followers_url":"https://api.github.com/users/tangjeff0/followers",
    "following_url":"https://api.github.com/users/tangjeff0/following{/other_user}",
    "gists_url":"https://api.github.com/users/tangjeff0/gists{/gist_id}",
    "starred_url":"https://api.github.com/users/tangjeff0/starred{/owner}{/repo}",
    "subscriptions_url":"https://api.github.com/users/tangjeff0/subscriptions",
    "organizations_url":"https://api.github.com/users/tangjeff0/orgs",
    "repos_url":"https://api.github.com/users/tangjeff0/repos",
    "events_url":"https://api.github.com/users/tangjeff0/events{/privacy}",
    "received_events_url":"https://api.github.com/users/tangjeff0/received_events",
    "type":"User",
    "site_admin":false
  },
  "labels":[
    {
      "id":2092499438,
      "node_id":"MDU6TGFiZWwyMDkyNDk5NDM4",
      "url":"https://api.github.com/repos/athensresearch/athens/labels/design:%20%E2%9C%85",
      "name":"design: ✅",
      "color":"6f6f6f",
      "default":false,
      "description":"design complete"
    },
    {
      "id":2092478123,
      "node_id":"MDU6TGFiZWwyMDkyNDc4MTIz",
      "url":"https://api.github.com/repos/athensresearch/athens/labels/type:%20%F0%9F%9A%80%20feature",
      "name":"type: 🚀 feature",
      "color":"0075ca",
      "default":false,
      "description":"Must be on https://github.com/athensresearch/athens/projects/2"
    }
  ],
  "state":"open",
  "locked":false,
  "assignee":null,
  "assignees":[],
  "milestone":null,
  "created_at":"2020-05-15 23:41:34 UTC",
  "updated_at":"2020-07-04 21:20:18 UTC",
  "closed_at":null,
  "author_association":"MEMBER",
  "active_lock_reason":null,
  "body":"# Link Filter\r\n\r\n- [ ] get list of links\r\n- [ ] implement in three places (see screenshot)\r\n  - page-level\r\n  - linked/unlinked references\r\n  - sidebar for pages and linked/unlinked references\r\n- [X] implement devcards #185 #186 \r\n\r\n## Locations\r\n\r\n![](https://firebasestorage.googleapis.com/v0/b/firescript-577a2.appspot.com/o/imgs%2Fapp%2Fjefftang%2Fr0xqGeAcAl.png?alt=media&token=eeb21399-12ce-47f8-8aca-6b6fa6b8879a)\r\n\r\n\r\n### Original Post\r\n\r\n<details>\r\n  <summary>Click to open</summary>\r\n\r\n\r\n## Design\r\n\r\n![Screen Shot 2020-06-27 at 11 06 28 AM](https://user-images.githubusercontent.com/8952138/85925407-414d9580-b866-11ea-88d9-2a5ef68a9a4b.png)\r\n\r\n\r\n### 06-28-2020\r\n\r\n#185 #186 #189 implements the following screenshot ([demo](https://athensresearch.github.io/athens/cards.html#!/athens.devcards.filters)). Next steps are to implement actual link parsing at the page-level, and then only include/exclude blocks based on those filters.\r\n\r\n### 05-15-2020\r\n\r\nAfter a certain number of links, it's quite difficult to manage all the filters. I believe some Roam users are now using `{{query}}`s to achieve a similar goal of filtering information.\r\n\r\nThe design space is likewise broad as in #26: What is the actual user goal and what might be some various solutions?\r\n\r\n![Screen Shot 2020-05-15 at 7 38 47 PM](https://user-images.githubusercontent.com/8952138/82104149-b2d0ea80-96e3-11ea-9ba5-0c5e685df405.png)\r\n\r\n</details>",
  "performed_via_github_app":null,
  "comments":[
    {
      "url":"https://api.github.com/repos/athensresearch/athens/issues/comments/634904305",
      "html_url":"https://github.com/athensresearch/athens/issues/65#issuecomment-634904305",
      "issue_url":"https://api.github.com/repos/athensresearch/athens/issues/65",
      "id":634904305,
      "node_id":"MDEyOklzc3VlQ29tbWVudDYzNDkwNDMwNQ==",
      "user":{
        "login":"jacobmorse",
        "id":48877,
        "node_id":"MDQ6VXNlcjQ4ODc3",
        "avatar_url":"https://avatars0.githubusercontent.com/u/48877?v=4",
        "gravatar_id":"",
        "url":"https://api.github.com/users/jacobmorse",
        "html_url":"https://github.com/jacobmorse",
        "followers_url":"https://api.github.com/users/jacobmorse/followers",
        "following_url":"https://api.github.com/users/jacobmorse/following{/other_user}",
        "gists_url":"https://api.github.com/users/jacobmorse/gists{/gist_id}",
        "starred_url":"https://api.github.com/users/jacobmorse/starred{/owner}{/repo}",
        "subscriptions_url":"https://api.github.com/users/jacobmorse/subscriptions",
        "organizations_url":"https://api.github.com/users/jacobmorse/orgs",
        "repos_url":"https://api.github.com/users/jacobmorse/repos",
        "events_url":"https://api.github.com/users/jacobmorse/events{/privacy}",
        "received_events_url":"https://api.github.com/users/jacobmorse/received_events",
        "type":"User",
        "site_admin":false
      },
      "created_at":"2020-05-27 19:51:31 UTC",
      "updated_at":"2020-07-04 21:10:08 UTC",
      "author_association":"NONE",
      "body":"I've still been thinking about this. We did some initial design exploration around making the filters easier to read and use.\r\n<img width=\"288\" alt=\"Frame 127\" src=\"https://user-images.githubusercontent.com/48877/83065359-fd7a2d00-a028-11ea-95f7-2196e30744e0.png\">\r\n\r\nThe idea was that, we could communicate the filter's status with color instead of requiring it to change locations into a separate \"added\" or \"excluded\" area. This concept could be used as a sidebar that leverages the vertical orientation to display the filters in a list. This type of component could also allow for filtering a long list of filters with a search bar at the top.\r\n\r\n<img width=\"288\" alt=\"Frame 126\" src=\"https://user-images.githubusercontent.com/48877/83065555-4cc05d80-a029-11ea-8bd8-dd513ca7f74e.png\">\r\n\r\nTo your point, @tangjeff0, the real question is, \"Do we want filters?\" Or, should we invest the design effort in making queries more accessible and easy to use? I lean toward the latter, but I would still like to hear from someone who uses this filter functionality a lot (if that person exists).",
      "performed_via_github_app":null
    }
  ]
}
